{"version":1,"resource":"file:///home/renji/asso/gcc/site/website/pages/templates/pages/legal_notices.html","entries":[{"id":"8QGT.html","timestamp":1693002909448},{"id":"1GiA.html","timestamp":1693002961867},{"id":"WVql.html","timestamp":1693002989322},{"id":"32hH.html","timestamp":1693003031540},{"id":"nHFB.html","timestamp":1693003060042},{"id":"XKWU.html","timestamp":1693003235779},{"id":"z9ca.html","timestamp":1693003267310},{"id":"zqtq.html","timestamp":1693058339715},{"id":"8Q8L.html","timestamp":1693058508275},{"id":"a608.html","timestamp":1693058728130},{"id":"hv7M.html","timestamp":1694128509329},{"id":"rbU0.html","timestamp":1694647430116},{"id":"keQs.html","timestamp":1694647458507},{"id":"oBQ0.html","timestamp":1699979826771}]}