{"version":1,"resource":"file:///home/renji/gistre/s9/lysa/tp4/src/ex2.rs","entries":[{"id":"22ED.rs","timestamp":1694723868306},{"id":"8PFa.rs","timestamp":1694723883498},{"id":"YLV7.rs","timestamp":1694723897274},{"id":"o9sw.rs","timestamp":1694723928299},{"id":"6YX2.rs","timestamp":1694723957141},{"id":"Yj4Y.rs","timestamp":1694723974736},{"id":"bytI.rs","timestamp":1694724053655},{"id":"eycg.rs","timestamp":1694724074800},{"id":"tJB4.rs","timestamp":1694724101045},{"id":"d4KN.rs","timestamp":1694724269450}]}