{"version":1,"resource":"file:///home/renji/asso/gcc/site/website/users/templates/users/password_reset/password_reset_email.html","entries":[{"id":"iH93.html","source":"renamed.source","timestamp":1699988400943},{"id":"bhPL.html","timestamp":1699988433802},{"id":"Lskt.html","source":"moved.source","timestamp":1699993105043},{"id":"DvUl.html","timestamp":1700007737003},{"id":"5oUn.html","timestamp":1700007951648},{"id":"O8Hj.html","timestamp":1700008028130},{"id":"nLbY.html","timestamp":1700008084347},{"id":"01NN.html","timestamp":1700008113597}]}